vggface/__init__.py
vggface/utils.py
vggface/vggface.py
vggface/resnet50/__init__.py
vggface/resnet50/layers.py
vggface/resnet50/resnet50.py
vggface-1.0.0.dist-info/LICENSE
vggface-1.0.0.dist-info/METADATA
vggface-1.0.0.dist-info/WHEEL
vggface-1.0.0.dist-info/top_level.txt
vggface-1.0.0.dist-info/RECORD
